boldi/_githooks_version.py
boldi/githooks.py
boldi_githooks-0.9.7.dist-info/METADATA
boldi_githooks-0.9.7.dist-info/WHEEL
boldi_githooks-0.9.7.dist-info/entry_points.txt
boldi_githooks-0.9.7.dist-info/RECORD
