Metadata-Version: 2.4
Name: boldi-githooks
Version: 0.9.7
Summary: boldi-githooks - Simple Git Hooks manager for Python projects
Author-email: Boldizsár Palotás <boldizsar.palotas@gmail.com>
License: MIT
Requires-Python: >=3.12
Requires-Dist: boldi-cli==0.9.7
Requires-Dist: rich
